evostra/__init__.py
evostra-1.0.1.dist-info/DESCRIPTION.rst
evostra-1.0.1.dist-info/METADATA
evostra-1.0.1.dist-info/RECORD
evostra-1.0.1.dist-info/WHEEL
evostra-1.0.1.dist-info/metadata.json
evostra-1.0.1.dist-info/top_level.txt
pyes/__init__.py
