Metadata-Version: 2.0
Name: evostra
Version: 1.0.1
Summary: Evolution Strategy Solver in Python
Home-page: https://github.com/alirezamika/evostra
Author: Alireza Mika
Author-email: alirezamika@gmail.com
License: MIT
Keywords: evolution strategy in machine learning - deep reinforcement learning
Platform: UNKNOWN
Classifier: Development Status :: 4 - Beta
Classifier: License :: OSI Approved :: MIT License
Classifier: Programming Language :: Python :: 2
Classifier: Programming Language :: Python :: 3
Requires-Dist: numpy
